canon/__init__.py
canon/manifest_masks.py
canon/type_masks.py
canon/data/__init__.py
canon/data/launch.py
canon/data/studio.py
canon/exceptions/__init__.py
canon-0.0.1.dist-info/LICENSE.md
canon-0.0.1.dist-info/METADATA
canon-0.0.1.dist-info/WHEEL
canon-0.0.1.dist-info/top_level.txt
canon-0.0.1.dist-info/RECORD
