Metadata-Version: 2.1
Name: canon
Version: 0.0.1
Summary: Canon is a tool for emulating the compression found in two of the Club Penguin mini-games.
Home-page: https://github.com/ketnipz/Canon
Author: Ben
Author-email: ben@solero.me
License: UNKNOWN
Platform: UNKNOWN
Classifier: Programming Language :: Python :: 2.7
Classifier: License :: OSI Approved :: MIT License
Classifier: Operating System :: OS Independent
